mscompress/_core.pyi
mscompress/_core.c
mscompress/__init__.py
mscompress/types.py
mscompress/utils.py
mscompress/py.typed
mscompress/_core.pyx
mscompress/_core.cpython-311-darwin.so
mscompress/mszx.py
mscompress/datasets/torch.py
mscompress/annotations/_base.py
mscompress/annotations/__init__.py
mscompress/annotations/psms/_base.py
mscompress/annotations/psms/_types.py
mscompress/annotations/psms/__init__.py
mscompress/annotations/psms/pepxml.py
mscompress/annotations/psms/reader.py
mscompress/annotations/psms/percolator.py
mscompress/metadata/_base.py
mscompress/metadata/_types.py
mscompress/metadata/__init__.py
mscompress/metadata/search.py
mscompress/metadata/_composite.py
mscompress/metadata/msz.py
mscompress-1.0.7.post2.dist-info/RECORD
mscompress-1.0.7.post2.dist-info/WHEEL
mscompress-1.0.7.post2.dist-info/top_level.txt
mscompress-1.0.7.post2.dist-info/METADATA
