Metadata-Version: 2.4
Name: mscompress
Version: 1.0.7.post2
Summary: Python bindings for mscompress, a compression library for mass spectrometry data
Author: Chris Grams
Author-email: chrisagrams@gmail.com
Requires-Python: >=3.9
Requires-Dist: mlcroissant>=1.0.0
Requires-Dist: numpy<2
Requires-Dist: zstandard>=0.19.0
Provides-Extra: dev
Requires-Dist: setuptools>=45; extra == "dev"
Requires-Dist: cython; extra == "dev"
Requires-Dist: numpy; extra == "dev"
Requires-Dist: pytest; extra == "dev"
Requires-Dist: pytest-cov; extra == "dev"
Requires-Dist: tomli; extra == "dev"
Provides-Extra: pytorch
Requires-Dist: torch>=2.0; extra == "pytorch"
Provides-Extra: all
Requires-Dist: mlcroissant>=1.0.0; extra == "all"
Requires-Dist: numpy<2; extra == "all"
Requires-Dist: zstandard>=0.19.0; extra == "all"
Requires-Dist: torch>=2.0; extra == "all"
Dynamic: author
Dynamic: author-email
